README.rst
setup.py
test/__init__.py
test/test_tkoutw.py
tkouter/__init__.py
tkouter/core.py
tkouter/errors.py
tkouter/fields.py
tkouter/settings.py
tkouter.egg-info/PKG-INFO
tkouter.egg-info/SOURCES.txt
tkouter.egg-info/dependency_links.txt
tkouter.egg-info/requires.txt
tkouter.egg-info/top_level.txt