Metadata-Version: 1.1
Name: tkouter
Version: 1.0.0a8
Summary: Package for creating tkinter layout by html
Home-page: https://github.com/dokelung/tkouter
Author: dokelung
Author-email: dokelung@gmail.com
License: MIT
Keywords: tkinter gui layout mvc html xml css
Platform: UNKNOWN
Classifier: Development Status :: 3 - Alpha
Classifier: Intended Audience :: Developers
Classifier: Topic :: Software Development :: Build Tools
Classifier: License :: OSI Approved :: MIT License
Classifier: Programming Language :: Python :: 3.3
Classifier: Programming Language :: Python :: 3.4
Classifier: Programming Language :: Python :: 3.5
Classifier: Programming Language :: Python :: 3.6
